agentslock/__init__.py
agentslock/cache.py
agentslock/cli.py
agentslock/config.py
agentslock/exceptions.py
agentslock/lockfile.py
agentslock/model.py
agentslock/paths.py
agentslock/resolve.py
agentslock/state.py
agentslock/sync.py
agentslock/ui.py
agentslock/util.py
agentslock/render/__init__.py
agentslock/render/base.py
agentslock/render/claude.py
agentslock/render/codex.py
agentslock/render/copilot.py
agentslock/render/gemini.py
agentslock-0.0.1.dist-info/METADATA
agentslock-0.0.1.dist-info/WHEEL
agentslock-0.0.1.dist-info/entry_points.txt
agentslock-0.0.1.dist-info/licenses/LICENSE
agentslock-0.0.1.dist-info/RECORD
