Metadata-Version: 2.4
Name: agentslock
Version: 0.0.1
Summary: A package manager for agents/skills/MCPs across AI CLI tools
Author-email: Oleh Kostromin <oleh@dataforce.solutions>
License: MIT
License-File: LICENSE
Keywords: agents,ai,claude,cli,codex,copilot,gemini,mcp,skills
Classifier: Environment :: Console
Classifier: Intended Audience :: Developers
Classifier: License :: OSI Approved :: MIT License
Classifier: Operating System :: OS Independent
Classifier: Programming Language :: Python :: 3
Classifier: Programming Language :: Python :: 3.11
Classifier: Programming Language :: Python :: 3.12
Classifier: Topic :: Software Development :: Build Tools
Classifier: Topic :: Utilities
Requires-Python: >=3.11
Requires-Dist: click>=8.1.0
Requires-Dist: rich>=13.0.0
Requires-Dist: tomlkit>=0.12.0
